foliant/preprocessors/escapecode.py
foliant/preprocessors/unescapecode.py
foliantcontrib_escapecode-1.0.9.dist-info/licenses/LICENSE
foliantcontrib_escapecode-1.0.9.dist-info/METADATA
foliantcontrib_escapecode-1.0.9.dist-info/WHEEL
foliantcontrib_escapecode-1.0.9.dist-info/top_level.txt
foliantcontrib_escapecode-1.0.9.dist-info/RECORD
